BboxTools.py
BboxTools-1.0.4.dist-info/METADATA
BboxTools-1.0.4.dist-info/WHEEL
BboxTools-1.0.4.dist-info/top_level.txt
BboxTools-1.0.4.dist-info/RECORD
