Metadata-Version: 2.1
Name: BboxTools
Version: 1.0.4
Summary: A python toolbox for bounding box operation
Home-page: https://github.com/Angtian/BboxTools
Author: Angtian Wang
Author-email: angtianwang@gmail.com
License: BSD
Platform: UNKNOWN
